kipoi_datasets/__init__.py
kipoi_datasets/bpnet_oskn.py
kipoi_datasets/core.py
kipoi_datasets-0.1.1.dist-info/LICENSE
kipoi_datasets-0.1.1.dist-info/METADATA
kipoi_datasets-0.1.1.dist-info/WHEEL
kipoi_datasets-0.1.1.dist-info/top_level.txt
kipoi_datasets-0.1.1.dist-info/RECORD
